[
    {
        "id": 1495,
        "name": "Renault/SCENIC/CG-007-VN1KXX",
        "driver_id": [
            337799,
            "Bassirou Cisse"
        ],
        "license_plate": "ZCG-007-VN1",
        "brand_id": [
            521,
            "Renault1"
        ],
        "model_id": [
            13111,
            "Renault/SCENIC1"
        ],
        "color": "Gris1",
        "co2": 0.01
    },
    {
        "id": 14449,
        "name": "Renault/SCENIC/CG-007-VNVV",
        "driver_id": [
            1331177,
            "LECHABLE ERIC"
        ],
        "license_plate": "BXCG-007-VN",
        "brand_id": [
            52,
            "Renault"
        ],
        "model_id": [
            1311,
            "Renault/SCENIC"
        ],
        "color": "Gris",
        "co2": 0.0
    }
]